nonebot_plugin_arxivRSS/__init__.py
nonebot_plugin_arxivRSS/config.py
nonebot_plugin_arxivRSS-0.2.0.dist-info/LICENSE
nonebot_plugin_arxivRSS-0.2.0.dist-info/METADATA
nonebot_plugin_arxivRSS-0.2.0.dist-info/WHEEL
nonebot_plugin_arxivRSS-0.2.0.dist-info/top_level.txt
nonebot_plugin_arxivRSS-0.2.0.dist-info/RECORD
