Metadata-Version: 2.1
Name: nonebot-plugin-arxivRSS
Version: 0.2.0
Summary: Plugin of Nonebot2. Subscribe and push Arxiv RSS daliy.
Author-email: LuckyOrz <lucky.wangyixuan@gmail.com>
License: MIT
Requires-Python: >=3.8
License-File: LICENSE
Requires-Dist: feedparser
Requires-Dist: nonebot2 >=2.0.0
Requires-Dist: httpx >=0.23.3
Requires-Dist: nonebot-adapter-onebot
Requires-Dist: nonebot-plugin-apscheduler
Requires-Dist: nonebot-plugin-localstore
